mpesaflow/__init__.py
mpesaflow/_base_client.py
mpesaflow/_client.py
mpesaflow/_compat.py
mpesaflow/_constants.py
mpesaflow/_exceptions.py
mpesaflow/_files.py
mpesaflow/_models.py
mpesaflow/_qs.py
mpesaflow/_resource.py
mpesaflow/_response.py
mpesaflow/_streaming.py
mpesaflow/_types.py
mpesaflow/_version.py
mpesaflow/pagination.py
mpesaflow/py.typed
mpesaflow/_utils/__init__.py
mpesaflow/_utils/_logs.py
mpesaflow/_utils/_proxy.py
mpesaflow/_utils/_reflection.py
mpesaflow/_utils/_streams.py
mpesaflow/_utils/_sync.py
mpesaflow/_utils/_transform.py
mpesaflow/_utils/_typing.py
mpesaflow/_utils/_utils.py
mpesaflow/lib/.keep
mpesaflow/resources/__init__.py
mpesaflow/resources/health.py
mpesaflow/resources/transactions.py
mpesaflow/resources/apps/__init__.py
mpesaflow/resources/apps/api_keys.py
mpesaflow/resources/apps/apps.py
mpesaflow/types/__init__.py
mpesaflow/types/app_create_params.py
mpesaflow/types/app_create_response.py
mpesaflow/types/app_delete_response.py
mpesaflow/types/app_list_params.py
mpesaflow/types/app_list_response.py
mpesaflow/types/application.py
mpesaflow/types/health_response.py
mpesaflow/types/health_retrieve_response.py
mpesaflow/types/transaction.py
mpesaflow/types/transaction_create_params.py
mpesaflow/types/transaction_create_response.py
mpesaflow/types/transaction_list_params.py
mpesaflow/types/transaction_list_response.py
mpesaflow/types/apps/__init__.py
mpesaflow/types/apps/api_key_create_params.py
mpesaflow/types/apps/api_key_create_response.py
mpesaflow/types/apps/api_key_delete_response.py
mpesaflow/types/apps/api_key_list_params.py
mpesaflow/types/apps/api_key_list_response.py
mpesaflow-4.4.0.dist-info/METADATA
mpesaflow-4.4.0.dist-info/WHEEL
mpesaflow-4.4.0.dist-info/licenses/LICENSE
mpesaflow-4.4.0.dist-info/RECORD
